trx_viewer/__main__.py
trx_viewer/expression_filter.py
trx_viewer/tests_model.py
trx_viewer/trx.py
trx_viewer/trx_viewer.py
trx_viewer/ViewerGUI/Main.qml
trx_viewer/ViewerGUI/OutputContainer.qml
trx_viewer/ViewerGUI/Style.qml
trx_viewer/ViewerGUI/failed.svg
trx_viewer/ViewerGUI/logo.svg
trx_viewer/ViewerGUI/passed.svg
trx_viewer/ViewerGUI/qmldir
trx_viewer-0.1.1.dist-info/METADATA
trx_viewer-0.1.1.dist-info/WHEEL
trx_viewer-0.1.1.dist-info/entry_points.txt
trx_viewer-0.1.1.dist-info/licenses/LICENSE
trx_viewer-0.1.1.dist-info/RECORD
